probit_socket_sdk/Authentication.py
probit_socket_sdk/ProBitSDK.py
probit_socket_sdk/WebSocketClient.py
probit_socket_sdk/__init__.py
probit_socket_sdk/test.py
probit_socket_sdk/constant/__init__.py
probit_socket_sdk/constant/channel_type.py
probit_socket_sdk/constant/filter_type.py
probit_socket_sdk/constant/socket_type.py
probit_socket_sdk/constant/type.py
probit_socket_sdk-0.0.2.dist-info/METADATA
probit_socket_sdk-0.0.2.dist-info/WHEEL
probit_socket_sdk-0.0.2.dist-info/top_level.txt
probit_socket_sdk-0.0.2.dist-info/RECORD
