Metadata-Version: 2.1
Name: probit_socket_sdk
Version: 0.0.2
Summary: Software Development Kit designated for Probit Global Exchange
Home-page: https://github.com/probitexchange/ProbitSocketSDK-python.git
Author: Probit Global
Author-email: dev@probit.com
Keywords: probit exchange,probit,probit global,probit sdk,probit socket,probit websocket
Classifier: Programming Language :: Python :: 3
Classifier: License :: OSI Approved :: MIT License
Requires-Python: >=3.12
Requires-Dist: requests
Requires-Dist: websocket-client
